LICENSE
MANIFEST.in
pyproject.toml
setup.cfg
setup.py
config/__init__.py
config/settings.py
config/urls.py
config/wsgi.py
django_fast_auth.egg-info/PKG-INFO
django_fast_auth.egg-info/SOURCES.txt
django_fast_auth.egg-info/dependency_links.txt
django_fast_auth.egg-info/requires.txt
django_fast_auth.egg-info/top_level.txt
fast_auth/__init__.py
fast_auth/apps.py
fast_auth/email_backend.py
fast_auth/forms.py
fast_auth/urls.py
fast_auth/utils.py
fast_auth/views.py
fast_auth/migrations/__init__.py
fast_auth/templates/fast_auth/logout.html
fast_auth/templates/fast_auth/signin.html
fast_auth/templates/fast_auth/signup.html