Metadata-Version: 2.1
Name: django-fast-auth
Version: 0.1
Summary: A Django app to conduct web-based polls.
Home-page: https://github.com/MironBerch/django-fast-auth
Author: MironBerch
Author-email: mironberchetov@gmail.com
License: MIT License
Classifier: Environment :: Web Environment
Classifier: Framework :: Django
Classifier: Framework :: Django :: 4.0
Classifier: Intended Audience :: Developers
Classifier: Operating System :: OS Independent
Classifier: Programming Language :: Python
Classifier: Programming Language :: Python :: 3
Classifier: Programming Language :: Python :: 3.8
Classifier: Programming Language :: Python :: 3.9
Requires-Python: >=3.8
License-File: LICENSE
